wshawk/__init__.py
wshawk/__main__.py
wshawk/advanced_cli.py
wshawk/cvss_calculator.py
wshawk/defensive_cli.py
wshawk/defensive_validation.py
wshawk/enhanced_reporter.py
wshawk/headless_xss_verifier.py
wshawk/interactive.py
wshawk/logger.py
wshawk/message_intelligence.py
wshawk/oast_provider.py
wshawk/payload_mutator.py
wshawk/payload_mutator_v3.py
wshawk/plugin_system.py
wshawk/rate_limiter.py
wshawk/scanner_v2.py
wshawk/scanner_v2_additions.py
wshawk/scanner_v2_new.py
wshawk/server_fingerprint.py
wshawk/session_hijacking_tester.py
wshawk/ssrf_test.py
wshawk/state_machine.py
wshawk/vulnerability_verifier.py
wshawk/wss_security_validator.py
wshawk/mutators/__init__.py
wshawk/mutators/base.py
wshawk/mutators/comments.py
wshawk/mutators/encoding.py
wshawk/mutators/polyglot.py
wshawk/mutators/tag_break.py
wshawk/payloads/command_injection.txt
wshawk/payloads/csv_injection.txt
wshawk/payloads/ldap_injection.txt
wshawk/payloads/malicious_origins.txt
wshawk/payloads/nosql_injection.txt
wshawk/payloads/open_redirect.txt
wshawk/payloads/path_traversal.txt
wshawk/payloads/sql_injection.txt
wshawk/payloads/ssti.txt
wshawk/payloads/xss.txt
wshawk/payloads/xxe.txt
wshawk/waf/__init__.py
wshawk/waf/detector.py
wshawk-2.0.5.dist-info/licenses/LICENSE
wshawk-2.0.5.dist-info/METADATA
wshawk-2.0.5.dist-info/WHEEL
wshawk-2.0.5.dist-info/entry_points.txt
wshawk-2.0.5.dist-info/top_level.txt
wshawk-2.0.5.dist-info/RECORD
