Metadata-Version: 2.4
Name: wshawk
Version: 2.0.5
Summary: Professional WebSocket security scanner with real vulnerability verification, session hijacking tests, and CVSS scoring
Home-page: https://github.com/noobforanonymous/wshawk
Author: Regaan
Project-URL: Homepage, https://github.com/noobforanonymous/wshawk
Project-URL: Bug Reports, https://github.com/noobforanonymous/wshawk/issues
Project-URL: Source, https://github.com/noobforanonymous/wshawk
Keywords: websocket,security,scanner,penetration-testing,bug-bounty,vulnerability,xss,sqli,session-hijacking,cvss,playwright,oast,waf-bypass
Classifier: Development Status :: 5 - Production/Stable
Classifier: Intended Audience :: Information Technology
Classifier: Intended Audience :: Developers
Classifier: Topic :: Security
Classifier: License :: OSI Approved :: MIT License
Classifier: Programming Language :: Python :: 3
Classifier: Programming Language :: Python :: 3.8
Classifier: Programming Language :: Python :: 3.9
Classifier: Programming Language :: Python :: 3.10
Classifier: Programming Language :: Python :: 3.11
Classifier: Programming Language :: Python :: 3.12
Classifier: Programming Language :: Python :: 3.13
Requires-Python: >=3.8
License-File: LICENSE
Requires-Dist: websockets>=12.0
Requires-Dist: playwright>=1.40.0
Requires-Dist: aiohttp>=3.9.0
Requires-Dist: PyYAML>=6.0
Dynamic: home-page
Dynamic: license-file
Dynamic: requires-python
